pywiscat/__init__.py
pywiscat/cli_helpers.py
pywiscat/wis2/__init__.py
pywiscat/wis2/catalogue.py
pywiscat-0.2.2.dist-info/LICENSE.md
pywiscat-0.2.2.dist-info/METADATA
pywiscat-0.2.2.dist-info/WHEEL
pywiscat-0.2.2.dist-info/entry_points.txt
pywiscat-0.2.2.dist-info/top_level.txt
pywiscat-0.2.2.dist-info/RECORD
