Metadata-Version: 2.1
Name: pywiscat
Version: 0.2.2
Summary: WMO WIS Catalogue analysis tool
Home-page: https://github.com/wmo-im/pywiscat
Author: Tom Kralidis
Author-email: tomkralidis@gmail.com
Maintainer: Tom Kralidis
Maintainer-email: tomkralidis@gmail.com
License: MIT
Keywords: wmo wis
Platform: all
Classifier: Development Status :: 4 - Beta
Classifier: Environment :: Console
Classifier: Intended Audience :: Developers
Classifier: Intended Audience :: Science/Research
Classifier: License :: OSI Approved :: MIT License
Classifier: Operating System :: OS Independent
Classifier: Programming Language :: Python
Classifier: Topic :: Scientific/Engineering :: Atmospheric Science
Classifier: Topic :: Scientific/Engineering :: GIS
Classifier: Topic :: Scientific/Engineering :: Information Analysis
License-File: LICENSE.md
Requires-Dist: click
Requires-Dist: emoji-country-flag
Requires-Dist: iso3166
Requires-Dist: prettytable
Requires-Dist: requests
